dapropy/Dapropy.py
dapropy/__init__.py
Dapropy-0.1.3.dist-info/LICENSE.txt
Dapropy-0.1.3.dist-info/METADATA
Dapropy-0.1.3.dist-info/WHEEL
Dapropy-0.1.3.dist-info/top_level.txt
Dapropy-0.1.3.dist-info/RECORD
