Metadata-Version: 2.1
Name: Dapropy
Version: 0.1.3
Summary: A Python library for automated preprocessing of mixed numeric, categorical, and text data.
Home-page: https://github.com/BlackIIIWhite/Dapropy
Author: Amit Subhash Agrahari
Author-email: agrahariamitindus45@gmail.com
License: MIT
Classifier: Programming Language :: Python :: 3
Classifier: License :: OSI Approved :: MIT License
Classifier: Operating System :: OS Independent
Requires-Python: >=3.8
License-File: LICENSE.txt
Requires-Dist: pandas>=1.3.0
Requires-Dist: numpy>=1.21.0
Requires-Dist: scikit-learn>=0.24.0
Requires-Dist: emoji>=1.6.0
Requires-Dist: nltk>=3.6.0
Requires-Dist: textblob>=0.15.3
Requires-Dist: joblib>=1.0.0
